odoo/addons/website_google_analytics_4/README.rst
odoo/addons/website_google_analytics_4/__init__.py
odoo/addons/website_google_analytics_4/__manifest__.py
odoo/addons/website_google_analytics_4/controllers/__init__.py
odoo/addons/website_google_analytics_4/controllers/website_sale.py
odoo/addons/website_google_analytics_4/i18n/it.po
odoo/addons/website_google_analytics_4/i18n/website_google_analytics_4.pot
odoo/addons/website_google_analytics_4/readme/CONFIGURE.rst
odoo/addons/website_google_analytics_4/readme/CONTRIBUTORS.rst
odoo/addons/website_google_analytics_4/readme/DESCRIPTION.rst
odoo/addons/website_google_analytics_4/readme/USAGE.rst
odoo/addons/website_google_analytics_4/static/description/icon.png
odoo/addons/website_google_analytics_4/static/description/index.html
odoo/addons/website_google_analytics_4/static/src/js/website_sale_tracking.js
odoo/addons/website_google_analytics_4/views/assets.xml
odoo/addons/website_google_analytics_4/views/website_templates.xml
odoo14_addon_website_google_analytics_4-14.0.1.1.0.dist-info/METADATA
odoo14_addon_website_google_analytics_4-14.0.1.1.0.dist-info/WHEEL
odoo14_addon_website_google_analytics_4-14.0.1.1.0.dist-info/top_level.txt
odoo14_addon_website_google_analytics_4-14.0.1.1.0.dist-info/RECORD
